blurpy/__about__.py
blurpy/__init__.py
blurpy/blur.py
blurpy/deps.py
blurpy/examples/run_blur.py
blurpy-0.0.7.dist-info/METADATA
blurpy-0.0.7.dist-info/WHEEL
blurpy-0.0.7.dist-info/licenses/LICENSE.txt
blurpy-0.0.7.dist-info/RECORD
