Metadata-Version: 2.4
Name: blurpy
Version: 0.0.7
Summary: A wrapper of Tekno's blur in Python 📦
Project-URL: Documentation, https://github.com/pro-grammer-sd/blur#readme
Project-URL: Issues, https://github.com/pro-grammer-sd/blur/issues
Project-URL: Source, https://github.com/pro-grammer-sd/blur
Author-email: Soumalya Das <geniussantu1983@gmail.com>
License-Expression: MIT
License-File: LICENSE.txt
Classifier: Development Status :: 4 - Beta
Classifier: Programming Language :: Python
Classifier: Programming Language :: Python :: 3.8
Classifier: Programming Language :: Python :: 3.9
Classifier: Programming Language :: Python :: 3.10
Classifier: Programming Language :: Python :: 3.11
Classifier: Programming Language :: Python :: 3.12
Classifier: Programming Language :: Python :: 3.13
Classifier: Programming Language :: Python :: Implementation :: CPython
Classifier: Programming Language :: Python :: Implementation :: PyPy
Requires-Python: >=3.8
